README.rst
setup.py
django_pxpay.egg-info/PKG-INFO
django_pxpay.egg-info/SOURCES.txt
django_pxpay.egg-info/dependency_links.txt
django_pxpay.egg-info/requires.txt
django_pxpay.egg-info/top_level.txt
pxpay/__init__.py
pxpay/gateway.py
pxpay/models.py