Metadata-Version: 1.1
Name: django-pxpay
Version: 0.2.3
Summary: PaymentExpress PxPay Gateway for Django
Home-page: http://github.com/pavel-shpilev/django-pxpay
Author: Pavel Shpilev
Author-email: p.shpilev@gmail.com
License: BSD
Keywords: PxPay,Payment,PaymentExpress,DPS,Django,Python
Platform: UNKNOWN
Classifier: Environment :: Web Environment
Classifier: Framework :: Django
Classifier: Intended Audience :: Developers
Classifier: License :: OSI Approved :: BSD License
Classifier: Operating System :: OS Independent
Classifier: Programming Language :: Python
